nomic/__init__.py
nomic/atlas.py
nomic/cli.py
nomic/client.py
nomic/client_models.py
nomic/data_inference.py
nomic/data_operations.py
nomic/dataset.py
nomic/embed.py
nomic/py.typed
nomic/settings.py
nomic/utils.py
nomic/aws/__init__.py
nomic/aws/sagemaker.py
nomic/pl_callbacks/__init__.py
nomic/pl_callbacks/pl_callback.py
nomic-3.9.0.dist-info/METADATA
nomic-3.9.0.dist-info/WHEEL
nomic-3.9.0.dist-info/entry_points.txt
nomic-3.9.0.dist-info/top_level.txt
nomic-3.9.0.dist-info/RECORD
