Metadata-Version: 2.4
Name: nomic
Version: 3.9.0
Summary: The official Nomic python client.
Home-page: https://github.com/nomic-ai/nomic
Author: nomic.ai
Author-email: support@nomic.ai
Classifier: License :: OSI Approved :: Apache Software License
Classifier: Programming Language :: Python :: 3
Requires-Dist: click
Requires-Dist: filetype<2,>=1.2.0
Requires-Dist: jsonlines
Requires-Dist: jsonschema<5,>=4.23.0
Requires-Dist: loguru
Requires-Dist: rich
Requires-Dist: requests
Requires-Dist: numpy
Requires-Dist: pandas
Requires-Dist: pydantic<3,>=2
Requires-Dist: tqdm
Requires-Dist: pyarrow
Requires-Dist: pillow
Requires-Dist: pyjwt
Provides-Extra: local
Requires-Dist: gpt4all<3,>=2.5.0; extra == "local"
Provides-Extra: aws
Requires-Dist: boto3; extra == "aws"
Requires-Dist: sagemaker; extra == "aws"
Provides-Extra: all
Requires-Dist: nomic[aws,local]; extra == "all"
Provides-Extra: dev
Requires-Dist: nomic[all]; extra == "dev"
Requires-Dist: black==24.3.0; extra == "dev"
Requires-Dist: coverage; extra == "dev"
Requires-Dist: pylint; extra == "dev"
Requires-Dist: pytest; extra == "dev"
Requires-Dist: isort; extra == "dev"
Requires-Dist: pyright<=1.1.377; extra == "dev"
Requires-Dist: myst-parser; extra == "dev"
Requires-Dist: mkdocs-material; extra == "dev"
Requires-Dist: mkautodoc; extra == "dev"
Requires-Dist: twine; extra == "dev"
Requires-Dist: mkdocstrings[python]; extra == "dev"
Requires-Dist: mkdocs-jupyter; extra == "dev"
Requires-Dist: pillow; extra == "dev"
Requires-Dist: cairosvg; extra == "dev"
Requires-Dist: pytorch-lightning; extra == "dev"
Requires-Dist: pandas; extra == "dev"
Dynamic: author
Dynamic: author-email
Dynamic: classifier
Dynamic: description
Dynamic: description-content-type
Dynamic: home-page
Dynamic: provides-extra
Dynamic: requires-dist
Dynamic: summary
